{
    "users": [
        {
            "name": "Aditya",
            "password": "aditya12345",
            "type": "staff"
        },
        {
            "name": "Kranti",
            "password": "kranti12345",
            "type": "staff"
        },
        {
            "name": "Shiva",
            "password": "shiva12345",
            "type": "staff"
        },
        {
            "name": "Guru",
            "password": "guru12345",
            "type": "admin"
        }
    ],
    "status": [
        "Delivered",
        "Created",
        "Cancelled",
        "Progress"
    ]
}